{
    "data": [{
        "from": "Anyone",
        "when": "During office hours",
        "to": "43991204"
    }, {
        "from": "Anyone",
        "when": "After office hours",
        "to": "Voicemail"
    }, {
        "from": "43985560",
        "when": "12:00 - 13:00",
        "to": "Voicemail"
    }, {
        "from": "43991007",
        "when": "During office hours",
        "to": "43229910"
    }, {
        "from": "43991005",
        "when": "During office hours",
        "to": "43229910"
    }]
}
